{
  "matchup": {
    "team1": "Denver Nuggets",
    "team2": "Cleveland Cavaliers",
    "home_team": "Denver Nuggets"
  },
  "current_season": {
    "team1": {
      "name": "Denver Nuggets",
      "record": "34-20",
      "conf_rank": 3,
      "games": 59,
      "ppg": 119.4,
      "opp_ppg": 111.3,
      "ortg": 114.1,
      "drtg": 110.3,
      "apg": 27.6,
      "rpg": 42.6,
      "topg": 12.9,
      "net_rating": 3.75,
      "fgp": 49.4,
      "tpp": 39.1,
      "last_ten": "5-5",
      "last_ten_pct": 0.5,
      "home_record": "14-10",
      "away_record": "20-9",
      "home_win_pct": 0.583,
      "away_win_pct": 0.69,
      "pace": 100.9,
      "recent_ppg": 120.3,
      "recent_margin": 1.6,
      "sos": 0.541,
      "sos_adjusted_net_rating": 4.16
    },
    "team2": {
      "name": "Cleveland Cavaliers",
      "record": "33-21",
      "conf_rank": 4,
      "games": 58,
      "ppg": 119.2,
      "opp_ppg": 115.6,
      "ortg": 113.7,
      "drtg": 110.7,
      "apg": 28.5,
      "rpg": 44.3,
      "topg": 14.6,
      "net_rating": 3.07,
      "fgp": 47.3,
      "tpp": 35.8,
      "last_ten": "8-2",
      "last_ten_pct": 0.8,
      "home_record": "17-11",
      "away_record": "15-10",
      "home_win_pct": 0.607,
      "away_win_pct": 0.6,
      "pace": 104.4,
      "recent_ppg": 122.7,
      "recent_margin": 11.4,
      "sos": 0.477,
      "sos_adjusted_net_rating": 2.84
    }
  },
  "schedule": {
    "team1": {
      "days_rest": 0,
      "streak": "L1",
      "games_last_7_days": 4,
      "recent_opponent_avg_win_pct": 0.541,
      "quality_wins": 0,
      "quality_losses": 5
    },
    "team2": {
      "days_rest": 0,
      "streak": "W4",
      "games_last_7_days": 3,
      "recent_opponent_avg_win_pct": 0.477,
      "quality_wins": 4,
      "quality_losses": 1
    }
  },
  "recent_games": {
    "team1": [
      {
        "vs": "Cleveland Cavaliers",
        "vs_record": "33-21",
        "vs_win_pct": 0.611,
        "result": "L",
        "score": "117-119",
        "home": true,
        "margin": -2,
        "date": "2026-02-10"
      },
      {
        "vs": "Chicago Bulls",
        "vs_record": "24-30",
        "vs_win_pct": 0.444,
        "result": "W",
        "score": "136-120",
        "home": false,
        "margin": 16,
        "date": "2026-02-08"
      },
      {
        "vs": "New York Knicks",
        "vs_record": "34-19",
        "vs_win_pct": 0.642,
        "result": "L",
        "score": "127-134",
        "home": false,
        "margin": -7,
        "date": "2026-02-05"
      },
      {
        "vs": "Detroit Pistons",
        "vs_record": "39-13",
        "vs_win_pct": 0.75,
        "result": "L",
        "score": "121-124",
        "home": false,
        "margin": -3,
        "date": "2026-02-04"
      },
      {
        "vs": "Oklahoma City Thunder",
        "vs_record": "41-13",
        "vs_win_pct": 0.759,
        "result": "L",
        "score": "111-121",
        "home": true,
        "margin": -10,
        "date": "2026-02-02"
      },
      {
        "vs": "LA Clippers",
        "vs_record": "25-27",
        "vs_win_pct": 0.481,
        "result": "W",
        "score": "122-109",
        "home": true,
        "margin": 13,
        "date": "2026-01-31"
      },
      {
        "vs": "Brooklyn Nets",
        "vs_record": "15-37",
        "vs_win_pct": 0.288,
        "result": "W",
        "score": "107-103",
        "home": true,
        "margin": 4,
        "date": "2026-01-30"
      },
      {
        "vs": "Detroit Pistons",
        "vs_record": "39-13",
        "vs_win_pct": 0.75,
        "result": "L",
        "score": "107-109",
        "home": true,
        "margin": -2,
        "date": "2026-01-28"
      },
      {
        "vs": "Milwaukee Bucks",
        "vs_record": "21-30",
        "vs_win_pct": 0.412,
        "result": "W",
        "score": "102-100",
        "home": false,
        "margin": 2,
        "date": "2026-01-24"
      },
      {
        "vs": "Washington Wizards",
        "vs_record": "14-38",
        "vs_win_pct": 0.269,
        "result": "W",
        "score": "107-97",
        "home": false,
        "margin": 10,
        "date": "2026-01-23"
      }
    ],
    "team2": [
      {
        "vs": "Denver Nuggets",
        "vs_record": "34-20",
        "vs_win_pct": 0.63,
        "result": "W",
        "score": "119-117",
        "home": false,
        "margin": 2,
        "date": "2026-02-10"
      },
      {
        "vs": "Sacramento Kings",
        "vs_record": "12-43",
        "vs_win_pct": 0.218,
        "result": "W",
        "score": "132-126",
        "home": false,
        "margin": 6,
        "date": "2026-02-08"
      },
      {
        "vs": "LA Clippers",
        "vs_record": "25-27",
        "vs_win_pct": 0.481,
        "result": "W",
        "score": "124-91",
        "home": false,
        "margin": 33,
        "date": "2026-02-05"
      },
      {
        "vs": "Portland Trail Blazers",
        "vs_record": "26-28",
        "vs_win_pct": 0.481,
        "result": "W",
        "score": "130-111",
        "home": false,
        "margin": 19,
        "date": "2026-02-02"
      },
      {
        "vs": "Phoenix Suns",
        "vs_record": "31-22",
        "vs_win_pct": 0.585,
        "result": "L",
        "score": "113-126",
        "home": false,
        "margin": -13,
        "date": "2026-01-31"
      },
      {
        "vs": "Los Angeles Lakers",
        "vs_record": "32-20",
        "vs_win_pct": 0.615,
        "result": "W",
        "score": "129-99",
        "home": true,
        "margin": 30,
        "date": "2026-01-29"
      },
      {
        "vs": "Orlando Magic",
        "vs_record": "28-24",
        "vs_win_pct": 0.538,
        "result": "W",
        "score": "114-98",
        "home": true,
        "margin": 16,
        "date": "2026-01-27"
      },
      {
        "vs": "Orlando Magic",
        "vs_record": "28-24",
        "vs_win_pct": 0.538,
        "result": "W",
        "score": "119-105",
        "home": false,
        "margin": 14,
        "date": "2026-01-25"
      },
      {
        "vs": "Sacramento Kings",
        "vs_record": "12-43",
        "vs_win_pct": 0.218,
        "result": "W",
        "score": "123-118",
        "home": true,
        "margin": 5,
        "date": "2026-01-24"
      },
      {
        "vs": "Charlotte Hornets",
        "vs_record": "25-29",
        "vs_win_pct": 0.463,
        "result": "W",
        "score": "94-87",
        "home": false,
        "margin": 7,
        "date": "2026-01-22"
      }
    ]
  },
  "players": {
    "team1": {
      "rotation": [
        {
          "name": "Jamal Murray",
          "ppg": 25.1,
          "plus_minus": 4.8,
          "games": 53
        },
        {
          "name": "Nikola Jokic",
          "ppg": 27.5,
          "plus_minus": 8.7,
          "games": 42
        },
        {
          "name": "Peyton Watson",
          "ppg": 14.4,
          "plus_minus": 3.3,
          "games": 54
        },
        {
          "name": "Cameron Johnson",
          "ppg": 11.2,
          "plus_minus": 7.0,
          "games": 35
        },
        {
          "name": "Christian Braun",
          "ppg": 9.9,
          "plus_minus": 6.8,
          "games": 22
        },
        {
          "name": "Aaron Gordon",
          "ppg": 17.5,
          "plus_minus": 8.3,
          "games": 26
        }
      ],
      "availability_concerns": [
        "Cameron Johnson (35/59 games)",
        "Christian Braun (22/59 games)",
        "Aaron Gordon (26/59 games)"
      ],
      "full_strength": false,
      "top_scorers": "Jokic 27.5, Murray 25.1, Gordon 17.5",
      "playmaker": "Nikola Jokic 10.2 APG",
      "hot_hand": "Jokic +8.7",
      "star_dependency": 23.0,
      "depth_rating": "balanced (4.8 MPG std dev)",
      "bench_scoring": 49.1,
      "injuries": []
    },
    "team2": {
      "rotation": [
        {
          "name": "Donovan Mitchell",
          "ppg": 28.2,
          "plus_minus": 5.5,
          "games": 53
        },
        {
          "name": "Evan Mobley",
          "ppg": 17.6,
          "plus_minus": 3.7,
          "games": 45
        },
        {
          "name": "Darius Garland",
          "ppg": 18.0,
          "plus_minus": -1.5,
          "games": 26
        },
        {
          "name": "Jaylon Tyson",
          "ppg": 13.5,
          "plus_minus": 0.9,
          "games": 53
        },
        {
          "name": "Jarrett Allen",
          "ppg": 14.0,
          "plus_minus": 3.3,
          "games": 45
        },
        {
          "name": "De'Andre Hunter",
          "ppg": 14.2,
          "plus_minus": 0.1,
          "games": 46
        }
      ],
      "availability_concerns": [
        "Darius Garland (26/58 games)",
        "Sam Merrill (31/58 games)",
        "Lonzo Ball (38/58 games)",
        "Dennis Schroder (3/58 games)"
      ],
      "full_strength": false,
      "top_scorers": "Mitchell 28.2, Garland 18.0, Mobley 17.6",
      "playmaker": "Darius Garland 6.9 APG (limited: 26 games)",
      "hot_hand": "Schroder +7.7 (limited: 3 games)",
      "star_dependency": 23.7,
      "depth_rating": "balanced (4.4 MPG std dev)",
      "bench_scoring": 45.2,
      "injuries": []
    }
  },
  "h2h": {
    "summary": {
      "total_games": 6,
      "team1_wins_all_time": 1,
      "team2_wins_all_time": 5,
      "team1_win_pct": 0.167,
      "team1_home_wins": 1,
      "team1_home_losses": 2,
      "team1_away_wins": 0,
      "team1_away_losses": 3,
      "avg_point_diff": -4.6,
      "team1_avg_points": 117.4,
      "team2_avg_points": 122.0,
      "last_5_games": [
        "Cleveland Cavaliers",
        "Cleveland Cavaliers",
        "Cleveland Cavaliers",
        "Cleveland Cavaliers",
        "Cleveland Cavaliers"
      ],
      "recent_trend": "team2_hot",
      "close_games": 2,
      "blowouts": 1
    },
    "patterns": {
      "avg_total": 239.4,
      "home_win_pct": 0.579,
      "high_scoring_pct": 1.0,
      "close_game_pct": 0.53
    },
    "recent": {
      "team1_wins_last_2_seasons": 0,
      "team2_wins_last_2_seasons": 4,
      "last_winner": "Cleveland Cavaliers",
      "home_team_home_record": "0-2",
      "games_last_2_seasons": 4
    },
    "quarters": {
      "avg_q1_total": 59.7,
      "avg_q2_total": 64.3,
      "avg_q3_total": 63.1,
      "avg_q4_total": 52.3,
      "avg_first_half": 124.0,
      "avg_second_half": 115.4,
      "team1_q1_avg": 29.0,
      "team2_q1_avg": 30.7,
      "team1_q4_avg": 24.1,
      "team2_q4_avg": 28.2,
      "halftime_leader_wins_pct": 0.83
    },
    "matchup_stats": {
      "team1": {
        "avg_fgp": 47.6,
        "avg_tpp": 38.3,
        "avg_rebounds": 41.1,
        "avg_assists": 28.2,
        "avg_turnovers": 13.3,
        "avg_disruption": 11.8
      },
      "team2": {
        "avg_fgp": 50.3,
        "avg_tpp": 40.0,
        "avg_rebounds": 43.9,
        "avg_assists": 30.6,
        "avg_turnovers": 14.3,
        "avg_disruption": 13.8
      }
    }
  },
  "totals_analysis": {
    "expected_total": 238.0,
    "total_diff_from_h2h": -0.8,
    "team1_h2h_scoring_diff": 2.0,
    "team2_h2h_scoring_diff": -2.8,
    "margin_volatility": 9.4,
    "h2h_total_variance": 22.3,
    "pace_adjusted_total": 233.8,
    "defense_factor": 110.5,
    "recent_scoring_trend": -3.2,
    "injury_adjusted_total": 215.7
  },
  "comparison": {
    "ppg": 0.2,
    "net_rating": 0.68,
    "form": -0.3,
    "turnovers": 1.7,
    "rebounds": -1.7,
    "fgp": 2.1,
    "three_pt_pct": 3.3,
    "pace": -3.5,
    "combined_pace": 102.7,
    "weighted_form": -9.8,
    "adjusted_net_rating": 1.32
  },
  "signals": [
    "Denver Nuggets playing second game today (fatigue factor)",
    "Cleveland Cavaliers playing second game today (fatigue factor)",
    "Denver Nuggets missing 23% of offense with key players limited",
    "Cleveland Cavaliers missing 24% of offense with key players limited",
    "Cleveland Cavaliers won 4 straight",
    "Cleveland Cavaliers stronger closer (+4.1 Q4 avg in H2H)",
    "Halftime leader wins 83% in this matchup",
    "H2H games front-loaded (1H avg 124.0 vs 2H avg 115.4)",
    "Denver Nuggets injury concerns: Cameron Johnson (35/59 games), Christian Braun (22/59 games)",
    "Cleveland Cavaliers injury concerns: Darius Garland (26/58 games), Sam Merrill (31/58 games)",
    "Cleveland Cavaliers hot form (8-2 L10)",
    "Cleveland Cavaliers solid on road (15-10)",
    "Denver Nuggets faced tougher schedule (SOS: 0.541 vs 0.477)",
    "Cleveland Cavaliers 4-0 in recent H2H",
    "Cleveland Cavaliers won 4+ of last 5 H2H meetings",
    "High-scoring matchup (100% H2H games over 220)",
    "Competitive series (53% decided by 5 or less)",
    "High-variance H2H (\u00b122.3 pts std dev in totals)",
    "Cleveland Cavaliers FG% elevated vs Denver Nuggets: 50.3% H2H vs 47.3% season",
    "Cleveland Cavaliers hot from 3 vs Denver Nuggets: 40.0% H2H vs 35.8% season"
  ],
  "api_game_id": 16295,
  "search_context": "### Injury Report\n**Cleveland Cavaliers:**\n- Evan Mobley (PF/C): Out - Left calf strain.[1][2][3][4]\n- Max Strus (SG): Out - Left foot surgery/Jones fracture.[1][2][4]\n- Emanuel Miller (SF): Out - G-League/two-way.[1]\n- Dean Wade (PF): Out - Left ankle sprain.[2][3]\n- Jaylon Tyson (SF): Available - Left ankle sprain (previously questionable).[2][3]\n- Tyrese Proctor (G): Available - Illness (previously questionable).[2][4]\n\n**Denver Nuggets:**\n- Tamar Bates (SG): Out - Left foot surgery.[1][4]\n- Curtis Jones (G): Out - G-League/development.[1]\n- Spencer Jones (SF): Out - Concussion protocol.[1][3][4]\n- Peyton Watson (SF): Out - Right leg/hamstring strain.[1][3][4]\n- Aaron Gordon (PF): Out - Hamstring.[3][4][9]\n- Nikola Joki\u0107 (C): Probable/game-time decision - Ankle (played in prior game).[1][3][4]\n- Christian Braun (SG): Probable - Ankle sprain (played in prior game).[1][3][5]\n- Jamal Murray (PG): Questionable - Left hip inflammation (played in prior game).[1][3][4]\n\nNote: Statuses reflect reports ahead of February 9 game; Joki\u0107, Murray, and Braun played in that matchup.[5][6]\n\n### Betting Lines\nNo current consensus spread, moneyline odds, or over/under total available in search results.\n\n### Line Movement\nNo information on opening lines or notable moves available in search results.\n\n### Recent News\nThe February 9 game resulted in a 119-117 Cavaliers win over the Nuggets, with James Harden and Donovan Mitchell leading Cleveland; Nuggets had balanced scoring from Joki\u0107 (22 pts, 14 reb, 11 ast), Murray (17 pts, 11 ast), Braun (20 pts), and Strawther (20 pts).[5][6] Denver has lost four of last five games.[6] No roster moves, rotation changes, or rest decisions reported in last 48 hours.[1][2][3][4][5][6]\n\n### Additional Context\n### Denver Nuggets Injury Status and Loss Streak Context\n\nAaron Gordon is out 4-6 weeks with a right hamstring strain, reinjured in a January 23-24, 2026, win over Milwaukee (16 minutes played: 13 points, 6 rebounds, 3 assists, 2 steals); this follows a prior absence from November 21, 2025, to January 4, 2026 (19 games missed).[1][2][3][4]\n\nNikola Joki\u0107 is out with a left knee bone bruise from December 30, 2025 (initial 4-week minimum, re-evaluation early February 2026); Nuggets are 9-5 without him.[2][3]\n\nJamal Murray is probable with right hamstring inflammation and left hip inflammation.[2]\n\nOther outs: Christian Braun (left ankle sprain), Cameron Johnson (right knee bone bruise), Tamar Bates (left foot surgery), Jonas Valan\u010di\u016bnas (right calf strain).[2][3]\n\nThese absences (Gordon, Joki\u0107, Braun, Johnson) leave four of five typical starters unavailable, forcing reliance on Peyton Watson (larger role), Spencer Jones, Bruce Brown, Zeke Nnaji, Julian Strawther, DaRon Holmes, Hunter Tyson; impacts frontcourt versatility and spacing, as Gordon averaged 17.7 points, 6.2 rebounds, 40% 3PT when healthy (23 games played).[2][3][4][5]\n\nNo direct data in results links specific lineups (e.g., without Gordon/Joki\u0107-Murray injuries) to a loss streak; Nuggets record 31-16 overall pre-injuries, third in West.[2]\n\n### Cleveland Cavaliers Injury Status and Rotation Impacts\n\nNo search results provide specifics on Evan Mobley or Max Strus absences, expanded roles for Cavaliers rotation players, or related stats/efficiency impacts.\n\n### Game-Relevant Context\n\nNuggets' injury-hit frontcourt (no Gordon/Joki\u0107) reduces defensive versatility and offensive spacing (Gordon's 40% 3PT, Joki\u0107's playmaking); Murray probable but managing dual inflammations.[2][4]\n\nCavaliers data absent; rematch implications unaddressed by results (e.g., prior matchup not detailed).[all]",
  "injury_impact": {
    "team1": {
      "out_players": [
        {
          "name": "Peyton Watson",
          "ppg": 14.4,
          "status": "Out"
        },
        {
          "name": "Aaron Gordon",
          "ppg": 17.5,
          "status": "Out"
        }
      ],
      "missing_ppg": 31.9,
      "adjusted_ppg_loss": 14.4
    },
    "team2": {
      "out_players": [
        {
          "name": "Evan Mobley",
          "ppg": 17.6,
          "status": "Out"
        }
      ],
      "missing_ppg": 17.6,
      "adjusted_ppg_loss": 7.9
    },
    "total_reduction": 22.3,
    "missing_ppg_diff": -6.5
  }
}